pydll78/__init__.py
pydll78/config78.py
pydll78/file_updater.py
pydll78/kafka78.py
pydll78/module_loader.py
pydll78-0.1.36.dist-info/entry_points.txt
pydll78-0.1.36.dist-info/LICENSE
pydll78-0.1.36.dist-info/METADATA
pydll78-0.1.36.dist-info/WHEEL
pydll78-0.1.36.dist-info/RECORD
