Metadata-Version: 2.1
Name: pydll78
Version: 0.1.36
Summary: python常用小工具包
Author: Frieda.Hu
Author-email: www778878net@189.cn
Requires-Python: >=3.12
Classifier: Programming Language :: Python :: 3
Classifier: Programming Language :: Python :: 3.12
Classifier: Programming Language :: Python :: 3.13
Requires-Dist: aiokafka (>=0.12.0,<0.13.0)
Requires-Dist: asyncio (>=3.4.3,<4.0.0)
Requires-Dist: configobj (>=5.0.9,<6.0.0)
Requires-Dist: log78 (==2.1.2)
Requires-Dist: requests (>=2.32.3,<3.0.0)
Requires-Dist: upinfopy (>=0.1.23,<0.2.0)
